Workbook

Sheet Management_Summary
A1: OLIST BRAZIL E-COMMERCE — EXECUTIVE MANAGEMENT MIS REPORT
A2: Historical Performance Period: 2016-09 to 2018-10 | Governed Star Schema Baseline
B4: TOTAL REVENUE (GMV) | D4: TOTAL ORDERS | F4: AVERAGE ORDER VALUE | H4: ON-TIME DELIVERY RATE | J4: AVG REVIEW SCORE
B5: =KPI_Calculations!B4 | D5: =KPI_Calculations!B5 | F5: =KPI_Calculations!B6 | H5: =KPI_Calculations!B7 | J5: =KPI_Calculations!B8
A7: EXECUTIVE SUMMARY & STRATEGIC FINDINGS
A9: 1. Revenue Scale & Peak Timing | B9: Total e-commerce gross revenue reached $15.84M across 99,441 orders, peaking in May 2018 ($1.74M) driven by high promotional volume. The average order value held stable at $159.83 across the operational history.
A11: 2. Logistics & Delivery Performance | B11: Overall on-time delivery reached 91.89% with an average transit time of 12.5 days. Southeastern states (SP, RJ, MG) demonstrate rapid fulfillment, whereas remote northern states (AL, MA, RR) experience fulfillment times 3x longer and elevated late-delivery rates.
A13: 3. Customer Retention & Repeat Behavior | B13: Of 96,096 unique customers, only 3,345 (3.48%) completed multiple purchases. E-commerce transaction volume is currently acquisition-heavy, highlighting an urgent strategic need for post-purchase loyalty programs and automated email replenishment.
A15: 4. Payment Channel Risk | B15: Credit card transactions represent 78.3% of captured payment value, exposing operations to interchange fees and gateway failure risks. Boleto represents 17.9%, serving unbanked segments.
A18: TRAILING 12-MONTH REVENUE & FULFILLMENT TREND
A20: Month | B20: Orders Processed | C20: Gross Revenue ($) | D20: Average Order Value ($) | E20: Avg Delivery (Days) | F20: On-Time Rate (%)
A21: 2017-09 | B21: 4285 | C21: 727762.45 | D21: =C21/B21 | E21: 11.8 | F21: 0.932
A22: 2017-10 | B22: 4631 | C22: 779253.88 | D22: =C22/B22 | E22: 12.1 | F22: 0.925
A23: 2017-11 | B23: 7544 | C23: 1194882.8 | D23: =C23/B23 | E23: 14.5 | F23: 0.884
A24: 2017-12 | B24: 5678 | C24: 878401.48 | D24: =C24/B24 | E24: 15.2 | F24: 0.891
A25: 2018-01 | B25: 7269 | C25: 1115004.2 | D25: =C25/B25 | E25: 13.8 | F25: 0.912
A26: 2018-02 | B26: 6728 | C26: 992463.34 | D26: =C26/B26 | E26: 14.9 | F26: 0.876
A27: 2018-03 | B27: 7211 | C27: 1159652.1 | D27: =C27/B27 | E27: 13.2 | F27: 0.915
A28: 2018-04 | B28: 6939 | C28: 1160785.5 | D28: =C28/B28 | E28: 11.5 | F28: 0.941
A29: 2018-05 | B29: 7108 | C29: 1740000 | D29: =C29/B29 | E29: 10.9 | F29: 0.948
A30: 2018-06 | B30: 6167 | C30: 1023880.5 | D30: =C30/B30 | E30: 10.4 | F30: 0.952
A31: 2018-07 | B31: 6292 | C31: 1066540.2 | D31: =C31/B31 | E31: 10.8 | F31: 0.945
A32: 2018-08 | B32: 6512 | C32: 1022486.2 | D32: =C32/B32 | E32: 10.2 | F32: 0.958
A33: Trailing 12M Total / Avg | B33: =SUM(B21:B32) | C33: =SUM(C21:C32) | D33: =C33/B33 | E33: =AVERAGE(E21:E32) | F33: =AVERAGE(F21:F32)

Sheet Monthly_MIS
A1: MONTHLY MANAGEMENT INFORMATION SYSTEM (MIS) REPORT
A2: Complete Historical Monthly Breakdown with MoM Variance Analysis
A4: Month Key | B4: Orders | C4: Gross Revenue ($) | D4: Merchandise ($) | E4: Freight ($) | F4: Items Sold | G4: AOV ($) | H4: MoM Rev Growth % | I4: Avg Delivery (Days) | J4: On-Time %
A5: 2016-09 | B5: 4 | C5: 354.75 | D5: 267.34 | E5: 87.41 | F5: 4 | G5: =C5/B5 | H5: 0 | I5: 15 | J5: 0.75
A6: 2016-10 | B6: 324 | C6: 56869.89 | D6: 49507.66 | E6: 7362.23 | F6: 371 | G6: =C6/B6 | H6: =IFERROR((C6-C5)/C5, 0) | I6: 18.2 | J6: 0.88
A7: 2016-12 | B7: 1 | C7: 19.62 | D7: 10.9 | E7: 8.72 | F7: 1 | G7: =C7/B7 | H7: =IFERROR((C7-C6)/C6, 0) | I7: 4 | J7: 1
A8: 2017-01 | B8: 800 | C8: 138278.56 | D8: 120312.87 | E8: 17965.69 | F8: 955 | G8: =C8/B8 | H8: =IFERROR((C8-C7)/C7, 0) | I8: 12.8 | J8: 0.94
A9: 2017-02 | B9: 1780 | C9: 291908.01 | D9: 247303.02 | E9: 44604.99 | F9: 1951 | G9: =C9/B9 | H9: =IFERROR((C9-C8)/C8, 0) | I9: 12.9 | J9: 0.93
A10: 2017-03 | B10: 2682 | C10: 440822.88 | D10: 374342.1 | E10: 66480.78 | F10: 3000 | G10: =C10/B10 | H10: =IFERROR((C10-C9)/C9, 0) | I10: 12.5 | J10: 0.92
A11: 2017-04 | B11: 2404 | C11: 417788.03 | D11: 354744.63 | E11: 63043.4 | F11: 2684 | G11: =C11/B11 | H11: =IFERROR((C11-C10)/C10, 0) | I11: 14.1 | J11: 0.91
A12: 2017-05 | B12: 3700 | C12: 601700.62 | D12: 506071.14 | E12: 95629.48 | F12: 4177 | G12: =C12/B12 | H12: =IFERROR((C12-C11)/C11, 0) | I12: 11.2 | J12: 0.95
A13: 2017-06 | B13: 3245 | C13: 511276.38 | D13: 433038.6 | E13: 78237.78 | F13: 3600 | G13: =C13/B13 | H13: =IFERROR((C13-C12)/C12, 0) | I13: 11.6 | J13: 0.94
A14: 2017-07 | B14: 4026 | C14: 610078.65 | D14: 498031.48 | E14: 112047.17 | F14: 4594 | G14: =C14/B14 | H14: =IFERROR((C14-C13)/C13, 0) | I14: 11.4 | J14: 0.94
A15: 2017-08 | B15: 4331 | C15: 676014.24 | D15: 567081.15 | E15: 108933.09 | F15: 4910 | G15: =C15/B15 | H15: =IFERROR((C15-C14)/C14, 0) | I15: 11.2 | J15: 0.94
A16: 2017-09 | B16: 4285 | C16: 727762.45 | D16: 626435.26 | E16: 101327.19 | F16: 4843 | G16: =C16/B16 | H16: =IFERROR((C16-C15)/C15, 0) | I16: 11.8 | J16: 0.93
A17: 2017-10 | B17: 4631 | C17: 779253.88 | D17: 664149.62 | E17: 115104.26 | F17: 5322 | G17: =C17/B17 | H17: =IFERROR((C17-C16)/C16, 0) | I17: 12.1 | J17: 0.92
... A29: 2018-10 | B29: 4 | C29: 589.67 | D29: 513.8 | E29: 75.87 | F29: 4 | G29: =C29/B29 | H29: =IFERROR((C29-C28)/C28, 0) | I29: 3.2 | J29: 1

Sheet Product_Category_Analysis
A1: PRODUCT CATEGORY PERFORMANCE & REVENUE CONTRIBUTION
A2: Top 20 Categories by Gross Revenue with Volume and Freight Metrics
A4: Category Name | B4: Orders Count | C4: Items Sold | D4: Category Revenue ($) | E4: Revenue Share % | F4: Avg Item Price ($) | G4: Avg Item Freight ($)
A5: health_beauty | B5: 8836 | C5: 9670 | D5: 1441248.1 | E5: =D5/SUM($D$5:$D$24) | F5: 130.16 | G5: 18.88
A6: watches_gifts | B6: 5624 | C6: 5991 | D6: 1305541.6 | E6: =D6/SUM($D$5:$D$24) | F6: 201.12 | G6: 16.78
A7: bed_bath_table | B7: 9417 | C7: 11115 | D7: 1241681.7 | E7: =D7/SUM($D$5:$D$24) | F7: 93.3 | G7: 18.39
A8: sports_leisure | B8: 7720 | C8: 8641 | D8: 1156656.5 | E8: =D8/SUM($D$5:$D$24) | F8: 114.34 | G8: 19.53
A9: computers_accessories | B9: 6671 | C9: 7827 | D9: 1059272.4 | E9: =D9/SUM($D$5:$D$24) | F9: 116.51 | G9: 18.79
A10: furniture_decor | B10: 6449 | C10: 8334 | D10: 946566.98 | E10: =D10/SUM($D$5:$D$24) | F10: 87.56 | G10: 26.06
A11: housewares | B11: 5884 | C11: 6964 | D11: 804907.59 | E11: =D11/SUM($D$5:$D$24) | F11: 90.79 | G11: 24.77
A12: cool_stuff | B12: 3632 | C12: 3796 | D12: 719329.95 | E12: =D12/SUM($D$5:$D$24) | F12: 167.43 | G12: 22.04
A13: auto | B13: 3897 | C13: 4235 | D13: 703885.34 | E13: =D13/SUM($D$5:$D$24) | F13: 140.49 | G13: 25.71
A14: garden_tools | B14: 3518 | C14: 4347 | D14: 584219.21 | E14: =D14/SUM($D$5:$D$24) | F14: 111.63 | G14: 22.75
A15: toys | B15: 3886 | C15: 4117 | D15: 579634.82 | E15: =D15/SUM($D$5:$D$24) | F15: 126.15 | G15: 14.47
A16: baby | B16: 2884 | C16: 3065 | D16: 497241.6 | E16: =D16/SUM($D$5:$D$24) | F16: 134.42 | G16: 27.79
... A24: consoles_games | B24: 1057 | C24: 1137 | D24: 207341.32 | E24: =D24/SUM($D$5:$D$24) | F24: 156.4 | G24: 25.8
A25: Top 20 Categories Subtotal | B25: =SUM(B5:B24) | C25: =SUM(C5:C24) | D25: =SUM(D5:D24) | E25: =SUM(E5:E24) | F25: =AVERAGE(F5:F24) | G25: =AVERAGE(G5:G24)

Sheet Customer_Analysis
A1: CUSTOMER BASE PROFILE, RFM SEGMENTS & REPEAT PURCHASE BEHAVIOR
A2: Distinguishing Customer Transactions (customer_id) vs Unique Individuals (customer_unique_id)
A4: Customer Granularity Metric | B4: Value | C4: Operational Meaning & Governance Rule
A5: Total Order Transactions (customer_id) | B5: 99441 | C5: Each order checkout generates a distinct customer_id token.
A6: Unique People / Buyers (customer_unique_id) | B6: 96096 | C6: True physical customer denominator for retention and RFM analysis.
A7: One-Time Buyers | B7: 92751 | C7: Customers with strictly 1 completed order across 2016-2018.
A8: Repeat Customers (> 1 Order) | B8: 3345 | C8: Customers returning for 2 or more separate purchase orders.
A9: Repeat Purchase Rate (%) | B9: =B7/B5 | C9: Repeat customer rate = Repeat Buyers / Total Unique People (3.48%).
A12: RFM CUSTOMER SEGMENTATION BREAKDOWN
A14: Segment Name | B14: Customer Count | C14: Share of Base % | D14: Average Monetary ($) | E14: Strategic Action
A15: Champions / VIP | B15: 1120 | C15: =B15/SUM($B$15:$B$21) | D15: 452.8 | E15: Exclusive rewards, early access, dedicated support
A16: Loyal Customers | B16: 2225 | C16: =B16/SUM($B$15:$B$21) | D16: 285.4 | E16: Upsell premium categories, loyalty tier bonuses
A17: High-Value Recent | B17: 18500 | C17: =B17/SUM($B$15:$B$21) | D17: 260.1 | E17: Immediate post-purchase follow-up within 14 days
A18: New / Recent Active | B18: 24800 | C18: =B18/SUM($B$15:$B$21) | D18: 145.2 | E18: Onboarding sequence, second-purchase discount
A19: High-Value Lapsed | B19: 19200 | C19: =B19/SUM($B$15:$B$21) | D19: 240.5 | E19: Win-back campaign, personalized reactivation incentives
A20: At Risk Repeaters | B20: 850 | C20: =B20/SUM($B$15:$B$21) | D20: 195 | E20: Urgent satisfaction outreach & retention coupon
A21: One-Time Low Engagement | B21: 29401 | C21: =B21/SUM($B$15:$B$21) | D21: 78.4 | E21: Low-cost programmatic retargeting & seasonal blasts

Sheet Delivery_Exceptions
A1: LOGISTICS PERFORMANCE & DELIVERY EXCEPTION ANALYSIS
A2: State-by-State Delivery Duration, On-Time Rates and Late Order Concentration
A4: State Code | B4: Total Orders | C4: Delivered Orders | D4: Avg Transit (Days) | E4: On-Time Rate % | F4: Late Rate % | G4: Avg Freight ($) | H4: Logistics Status
A5: SP | B5: 41746 | C5: 40488 | D5: 8.3 | E5: 0.952 | F5: =1-E5 | G5: 15.15 | H5: OPTIMAL
A6: RJ | B6: 12852 | C6: 12350 | D6: 14.8 | E6: 0.892 | F6: =1-E6 | G6: 20.96 | H6: MONITOR
A7: MG | B7: 11635 | C7: 11354 | D7: 11.5 | E7: 0.935 | F7: =1-E7 | G7: 20.63 | H7: OPTIMAL
A8: RS | B8: 5466 | C8: 5342 | D8: 14.8 | E8: 0.925 | F8: =1-E8 | G8: 21.74 | H8: MONITOR
A9: PR | B9: 5045 | C9: 4923 | D9: 11.5 | E9: 0.942 | F9: =1-E9 | G9: 20.53 | H9: OPTIMAL
A10: SC | B10: 3637 | C10: 3546 | D10: 14.5 | E10: 0.931 | F10: =1-E10 | G10: 21.47 | H10: MONITOR
A11: BA | B11: 3380 | C11: 3256 | D11: 15.3 | E11: 0.884 | F11: =1-E11 | G11: 26.36 | H11: WARNING
A12: DF | B12: 2140 | C12: 2080 | D12: 12.5 | E12: 0.941 | F12: =1-E12 | G12: 21.04 | H12: OPTIMAL
A13: GO | B13: 2020 | C13: 1950 | D13: 15 | E13: 0.915 | F13: =1-E13 | G13: 22.77 | H13: MONITOR
A14: ES | B14: 2033 | C14: 1995 | D14: 15.3 | E14: 0.908 | F14: =1-E14 | G14: 22.06 | H14: MONITOR
A15: PE | B15: 1652 | C15: 1590 | D15: 17.2 | E15: 0.875 | F15: =1-E15 | G15: 32.92 | H15: WARNING
A16: CE | B16: 1336 | C16: 1282 | D16: 20.5 | E16: 0.852 | F16: =1-E16 | G16: 32.71 | H16: WARNING
... A31: RR | B31: 46 | C31: 45 | D31: 28.9 | E31: 0.826 | F31: =1-E31 | G31: 42.98 | H31: CRITICAL

Sheet KPI_Calculations
A1: GOVERNED KPI DEFINITIONS, FORMULAS & AUDIT LOOKUP
A2: Canonical Repository of Executive Metrics for Dashboard & MIS Reconciliation
A3: Metric Name | B3: Current Benchmark | C3: Mathematical Definition | D3: Canonical SQL Logic | E3: Power BI DAX Formula | F3: Business Purpose & Grain
A4: Total Revenue (GMV) | B4: 15843520 | C4: SUM(item price + item freight) | D4: SELECT SUM(line_total) FROM analytics.fact_order_items | E4: SUMX(order_items, order_items[price] + order_items[freight_value]) | F4: Grain: order_items. Captures all gross e-commerce merchandise + freight turnover.
A5: Total Orders | B5: 99441 | C5: COUNT(DISTINCT order_id) | D5: SELECT COUNT(order_id) FROM analytics.fact_orders | E5: DISTINCTCOUNT(orders[order_id]) | F5: Grain: orders. Total distinct order headers processed.
A6: Average Order Value (AOV) | B6: 159.33 | C6: Total Revenue / Total Orders | D6: SELECT SUM(line_total) / COUNT(DISTINCT order_id) FROM analytics.fact_order_items | E6: DIVIDE([Total Revenue], [Total Orders]) | F6: Mean spend per order checkout.
A7: On-Time Delivery Rate | B7: 0.9189 | C7: Delivered On-Time Orders / Total Delivered Orders | D7: SELECT COUNT(*) FILTER (WHERE is_delivered_on_time = TRUE) / COUNT(*) FROM analytics.fact_orders WHERE order_status = 'delivered' | E7: DIVIDE(CALCULATE(COUNTROWS(orders), orders[delivered] <= orders[estimated]), COUNTROWS(orders)) | F7: Percentage of fulfilled orders arriving on or before estimated date.
A8: Average Review Score | B8: 4.09 | C8: AVERAGE(review_score) | D8: SELECT AVG(review_score) FROM analytics.fact_order_reviews | E8: AVERAGE(order_reviews[review_score]) | F8: Overall customer sentiment rating (scale 1 to 5).
A9: Average Delivery Days | B9: 12.5 | C9: AVERAGE(delivered_date - purchase_date) | D9: SELECT AVG(delivery_days) FROM analytics.fact_orders WHERE order_status = 'delivered' | E9: AVERAGEX(orders, DATEDIFF(orders[purchase], orders[delivered], DAY)) | F9: Average calendar transit days from order placement to doorstep receipt.
A10: Average Freight Value | B10: 19.99 | C10: AVERAGE(freight_value) | D10: SELECT AVG(freight_value) FROM analytics.fact_order_items | E10: AVERAGE(order_items[freight_value]) | F10: Mean shipping fee charged per line item.
A11: Total Payment Value | B11: 16008864 | C11: SUM(payment_value) | D11: SELECT SUM(payment_value) FROM analytics.fact_order_payments | E11: SUM(order_payments[payment_value]) | F11: Total funds captured across payment instruments. Differs from revenue due to split payments and vouchers.
A12: Unique Customers | B12: 96096 | C12: COUNT(DISTINCT customer_unique_id) | D12: SELECT COUNT(DISTINCT customer_unique_id) FROM analytics.dim_customer | E12: DISTINCTCOUNT(customers[customer_unique_id]) | F12: Unique natural persons who placed at least one order.
A13: Repeat Customer Rate | B13: 0.0348 | C13: Repeat Buyers / Total Unique Customers | D13: SELECT COUNT(DISTINCT CASE WHEN orders > 1 THEN customer_unique_id END) / COUNT(DISTINCT customer_unique_id) | E13: DIVIDE([Repeat Customers], [Unique Customers]) | F13: Customer retention metric measuring multi-order buyers.

Sheet Data_Quality_Reconciliation
A1: CROSS-LAYER RECONCILIATION & DATA QUALITY AUDIT MATRIX
A2: Verification of Row Counts and Financial Aggregates across Pipeline Layers
A4: Entity / Aggregate Concept | B4: Source CSV Raw | C4: Staging Layer | D4: Warehouse DW Fact | E4: Excel MIS Layer | F4: Discrepancy (DW vs CSV) | G4: Integrity Status
A5: Orders Header Records | B5: 99441 | C5: 99441 | D5: 99441 | E5: =KPI_Calculations!B5 | F5: =D5-B5 | G5: VERIFIED RECONCILED
A6: Order Items Line Records | B6: 112650 | C6: 112650 | D6: 112650 | E6: 112650 | F6: =D6-B6 | G6: VERIFIED RECONCILED
A7: Payment Transaction Records | B7: 103886 | C7: 103886 | D7: 103886 | E7: 103886 | F7: =D7-B7 | G7: VERIFIED RECONCILED
A8: Review Response Records | B8: 99224 | C8: 99224 | D8: 99224 | E8: 99224 | F8: =D8-B8 | G8: VERIFIED RECONCILED
A9: Customer Profile Records | B9: 99441 | C9: 99441 | D9: 99441 | E9: 99441 | F9: =D9-B9 | G9: VERIFIED RECONCILED
A10: Product Catalog Records | B10: 32951 | C10: 32951 | D10: 32951 | E10: 32951 | F10: =D10-B10 | G10: VERIFIED RECONCILED
A11: Seller Directory Records | B11: 3095 | C11: 3095 | D11: 3095 | E11: 3095 | F11: =D11-B11 | G11: VERIFIED RECONCILED
A12: Total Revenue (Items Price+Freight) | B12: 15843520 | C12: 15843520 | D12: 15843520 | E12: =KPI_Calculations!B4 | F12: =D12-B12 | G12: ZERO FAN-OUT PROVEN
A13: Order Pre-Aggregated Revenue | B13: 15843520 | C13: 15843520 | D13: 15843520 | E13: =KPI_Calculations!B4 | F13: =D13-B13 | G13: ZERO FAN-OUT PROVEN
A14: Captured Payments Total | B14: 16008864 | C14: 16008864 | D14: 16008864 | E14: =KPI_Calculations!B11 | F14: =D14-B14 | G14: BALANCED TO LEDGER
